dropmate_py/__init__.py
dropmate_py/audit_errors.py
dropmate_py/audits.py
dropmate_py/cli.py
dropmate_py/log_utils.py
dropmate_py/parser.py
dropmate_py-1.0.0.dist-info/LICENSE
dropmate_py-1.0.0.dist-info/METADATA
dropmate_py-1.0.0.dist-info/WHEEL
dropmate_py-1.0.0.dist-info/entry_points.txt
dropmate_py-1.0.0.dist-info/RECORD
