Metadata-Version: 2.1
Name: dropmate-py
Version: 1.0.0
Summary: Python helpers for the EDC Dropmate
Home-page: https://github.com/sco1/
Author: sco1
Author-email: sco1.git@gmail.com
Requires-Python: >=3.11,<4.0
Classifier: Development Status :: 5 - Production/Stable
Classifier: Intended Audience :: Developers
Classifier: License :: OSI Approved :: MIT License
Classifier: Operating System :: OS Independent
Classifier: Programming Language :: Python :: 3
Classifier: Programming Language :: Python :: 3.11
Classifier: Programming Language :: Python :: 3 :: Only
Classifier: Programming Language :: Python :: 3.12
Classifier: Typing :: Typed
Requires-Dist: python-dotenv (>=1.0,<2.0)
Requires-Dist: sco1-misc (>=0.1,<0.2)
Requires-Dist: typer (>=0.9,<0.10)
Project-URL: Issue Tracker, https://github.com/sco1/dropmate-py/issues
Project-URL: Repository, https://github.com/sco1/dropmate-py
